{
    "statistics": {
        "total_playlists": 3,
        "total_videos": 3,
        "playlist_counts": [
            {
                "name": "测试001",
                "count": 1
            },
            {
                "name": "测试002",
                "count": 1
            },
            {
                "name": "测试003",
                "count": 1
            }
        ]
    },
    "playlists": [
        {
            "name": "测试001",
            "videos": [
                {
                    "number": 1,
                    "url": "https://www.youtube.com/watch?v=GGr0wrA2P40",
                    "title": "《成功与运气》成功背后运气之谜,掌握幸运密码, 成功背后的运气学,成功与运气,精通人生运作法则听书财富 Listening to Forture",
                    "playlist": "测试001"
                }
            ]
        },
        {
            "name": "测试002",
            "videos": [
                {
                    "number": 1,
                    "url": "https://www.youtube.com/watch?v=-zV8x5mjQuY",
                    "title": "《阅人无数》阅尽人生风景，洞悉人性智者之路，洞悉他人,阅人无数，打破社交迷局的人际智慧法则·听书财富 Listening to Forture",
                    "playlist": "测试002"
                }
            ]
        },
        {
            "name": "测试003",
            "videos": [
                {
                    "number": 1,
                    "url": "https://www.youtube.com/watch?v=-C45335azW4",
                    "title": "《语言的魔力》揭示语言魔力,言辞之中创造奇迹, 口才大師,語言的魔力,創造令人印象深刻的口才听书财富 Listening to Forture",
                    "playlist": "测试003"
                }
            ]
        }
    ]
}